{
    "aggregated_rating": 70.0, 
    "aggregated_rating_count": 1, 
    "alternative_names": [
        {
            "comment": "Japanese title", 
            "name": "\u30c7\u30a3\u30fc\u30d7\u30e9\u30d3\u30ea\u30f3\u30b9 D\u012bpu Rabirinsu"
        }
    ], 
    "category": 0, 
    "cover": {
        "cloudinary_id": "pjnvrqoqfotah17amo7r", 
        "height": 586, 
        "url": "//images.igdb.com/igdb/image/upload/t_thumb/pjnvrqoqfotah17amo7r.jpg", 
        "width": 511
    }, 
    "created_at": 1468841712301, 
    "esrb": {
        "rating": 4
    }, 
    "first_release_date": 1154995200000, 
    "games": [
        26766, 
        36926, 
        36534, 
        18398, 
        19333, 
        11214, 
        47823, 
        25300, 
        12632, 
        55092
    ], 
    "genres": [
        12, 
        31
    ], 
    "id": 20552, 
    "keywords": [
        226, 
        227, 
        296, 
        1026, 
        1513, 
        1935, 
        2154, 
        4330, 
        4471, 
        5559, 
        13106
    ], 
    "name": "Deep Labyrinth", 
    "pegi": {
        "rating": 2
    }, 
    "platforms": [
        20
    ], 
    "popularity": 1.0, 
    "publishers": [
        818
    ], 
    "release_dates": [
        {
            "category": 0, 
            "date": 1154995200000, 
            "human": "2006-Aug-08", 
            "m": 8, 
            "platform": 20, 
            "region": 2, 
            "y": 2006
        }, 
        {
            "category": 0, 
            "date": 1158278400000, 
            "human": "2006-Sep-15", 
            "m": 9, 
            "platform": 20, 
            "region": 8, 
            "y": 2006
        }
    ], 
    "screenshots": [
        {
            "cloudinary_id": "ad0k9kyb7eufba2wocys", 
            "height": 384, 
            "url": "//images.igdb.com/igdb/image/upload/t_thumb/ad0k9kyb7eufba2wocys.jpg", 
            "width": 256
        }, 
        {
            "cloudinary_id": "lyidphtomohi3gxuh83j", 
            "height": 384, 
            "url": "//images.igdb.com/igdb/image/upload/t_thumb/lyidphtomohi3gxuh83j.jpg", 
            "width": 256
        }, 
        {
            "cloudinary_id": "b1riced0uupp4ye4fasg", 
            "height": 384, 
            "url": "//images.igdb.com/igdb/image/upload/t_thumb/b1riced0uupp4ye4fasg.jpg", 
            "width": 256
        }, 
        {
            "cloudinary_id": "rrmsjq5ddxdgfjdeottt", 
            "height": 384, 
            "url": "//images.igdb.com/igdb/image/upload/t_thumb/rrmsjq5ddxdgfjdeottt.jpg", 
            "width": 256
        }, 
        {
            "cloudinary_id": "mbr1ggo7e4mebj8wiaeo", 
            "height": 384, 
            "url": "//images.igdb.com/igdb/image/upload/t_thumb/mbr1ggo7e4mebj8wiaeo.jpg", 
            "width": 256
        }, 
        {
            "cloudinary_id": "mh85sszicjr8nm50ra9j", 
            "height": 384, 
            "url": "//images.igdb.com/igdb/image/upload/t_thumb/mh85sszicjr8nm50ra9j.jpg", 
            "width": 256
        }, 
        {
            "cloudinary_id": "s6ck8fkk4maxlncztppu", 
            "height": 384, 
            "url": "//images.igdb.com/igdb/image/upload/t_thumb/s6ck8fkk4maxlncztppu.jpg", 
            "width": 256
        }, 
        {
            "cloudinary_id": "vbgbfxskkv6ipi335j3x", 
            "height": 384, 
            "url": "//images.igdb.com/igdb/image/upload/t_thumb/vbgbfxskkv6ipi335j3x.jpg", 
            "width": 256
        }, 
        {
            "cloudinary_id": "cgee3ikfxhs2hyb5ody1", 
            "height": 384, 
            "url": "//images.igdb.com/igdb/image/upload/t_thumb/cgee3ikfxhs2hyb5ody1.jpg", 
            "width": 256
        }, 
        {
            "cloudinary_id": "yvlj4gwbakcr8dyinisv", 
            "height": 384, 
            "url": "//images.igdb.com/igdb/image/upload/t_thumb/yvlj4gwbakcr8dyinisv.jpg", 
            "width": 256
        }, 
        {
            "cloudinary_id": "tu9c9wq5qch4jgtkjzf3", 
            "height": 384, 
            "url": "//images.igdb.com/igdb/image/upload/t_thumb/tu9c9wq5qch4jgtkjzf3.jpg", 
            "width": 256
        }, 
        {
            "cloudinary_id": "sbgkr90h79oajhrfr2hs", 
            "height": 384, 
            "url": "//images.igdb.com/igdb/image/upload/t_thumb/sbgkr90h79oajhrfr2hs.jpg", 
            "width": 256
        }
    ], 
    "slug": "deep-labyrinth", 
    "summary": "One summer afternoon, Shawn goes for a drive with his parents and dog, Ace, but the family car suffers a flat tire in front of an abandoned mansion. Ace is upset by something inside the mansion and leaps out of the car to investigate. Shawn's parents follow Ace, but fail to return. As Shawn tentatively approaches the dilapidated structure, the entrance door swings open, and he's drawn into a magical vortex. Reunited with Ace, Shawn must travel into the heart of the Deep Labyrinth to rescue his parents. \n \nThere is also a second story of another man who gets sucked into a warphole while talking on his cellphone. He finds himself trapped in a labyrinth. As he journeys through, he is forced to reconcile the past, and realize what it is that traps him in the labyrinth. \n \nEach scenario has multiple endings based on the actions and performance of the player, as well as helpful items sequential playthroughs, to aid unlocking all the secrets of the labyrinth.", 
    "tags": [
        268435468, 
        268435487, 
        536871138, 
        536871139, 
        536871208, 
        536871938, 
        536872425, 
        536872847, 
        536873066, 
        536875242, 
        536875383, 
        536876471, 
        536884018
    ], 
    "total_rating": 70.0, 
    "total_rating_count": 1, 
    "updated_at": 1518055190477, 
    "url": "https://www.igdb.com/games/deep-labyrinth"
}