{
    "category": 0, 
    "created_at": 1499424517287, 
    "first_release_date": 766627200000, 
    "genres": [
        14
    ], 
    "id": 44417, 
    "name": "Derby Jockey", 
    "platforms": [
        19
    ], 
    "popularity": 1.333333333333333, 
    "release_dates": [
        {
            "category": 0, 
            "date": 766627200000, 
            "human": "1994-Apr-18", 
            "m": 4, 
            "platform": 19, 
            "region": 8, 
            "y": 1994
        }
    ], 
    "slug": "derby-jockey", 
    "summary": "Derby Jockey is a Sports game, developed by Graphic Research and published by Asmik Ace Entertainment, Inc, which was released in Japan in 1994.", 
    "updated_at": 1500623756542, 
    "url": "https://www.igdb.com/games/derby-jockey"
}