{
    "category": 0, 
    "created_at": 1500030119797, 
    "first_release_date": 1029715200000, 
    "genres": [
        15
    ], 
    "id": 49845, 
    "name": "Tokimeki Dream Series 1: Ohanaya-san ni Narou!", 
    "platforms": [
        24
    ], 
    "popularity": 1.333333333333333, 
    "release_dates": [
        {
            "category": 0, 
            "date": 1029715200000, 
            "human": "2002-Aug-19", 
            "m": 8, 
            "platform": 24, 
            "region": 8, 
            "y": 2002
        }
    ], 
    "slug": "tokimeki-dream-series-1-ohanaya-san-ni-narou", 
    "summary": "Tokimeki Dream Series 1: Ohanaya-san ni Narou! is a Strategy game, published by MTO, which was released in Japan in 2002.", 
    "updated_at": 1500377466109, 
    "url": "https://www.igdb.com/games/tokimeki-dream-series-1-ohanaya-san-ni-narou"
}