{
    "category": 0, 
    "cover": {
        "cloudinary_id": "cb3juw7meyhfxdr111ot", 
        "height": 409, 
        "url": "//images.igdb.com/igdb/image/upload/t_thumb/cb3juw7meyhfxdr111ot.jpg", 
        "width": 283
    }, 
    "created_at": 1499965482414, 
    "first_release_date": 608860800000, 
    "games": [
        27314, 
        26766, 
        19448, 
        25300, 
        36950, 
        13189, 
        17469, 
        25222, 
        25311, 
        41895
    ], 
    "genres": [
        31
    ], 
    "id": 48427, 
    "keywords": [
        970, 
        1027, 
        1212, 
        7450
    ], 
    "name": "Mindseeker", 
    "platforms": [
        18
    ], 
    "popularity": 1.666666666666667, 
    "release_dates": [
        {
            "category": 0, 
            "date": 608860800000, 
            "human": "1989-Apr-18", 
            "m": 4, 
            "platform": 18, 
            "region": 5, 
            "y": 1989
        }, 
        {
            "category": 0, 
            "date": 611452800000, 
            "human": "1989-May-18", 
            "m": 5, 
            "platform": 18, 
            "region": 8, 
            "y": 1989
        }
    ], 
    "slug": "mindseeker", 
    "summary": "Mindseeker is an Adventure game, developed and published by Namco, which was released in Japan in 1989.", 
    "tags": [
        18, 
        268435487, 
        536871882, 
        536871939, 
        536872124, 
        536878362
    ], 
    "themes": [
        18
    ], 
    "updated_at": 1516751737186, 
    "url": "https://www.igdb.com/games/mindseeker"
}