{
    "category": 0, 
    "cover": {
        "cloudinary_id": "jcr30awbjxh2uegtq1bw", 
        "height": 1395, 
        "url": "//images.igdb.com/igdb/image/upload/t_thumb/jcr30awbjxh2uegtq1bw.jpg", 
        "width": 1000
    }, 
    "created_at": 1508051773054, 
    "developers": [
        8265
    ], 
    "first_release_date": 573955200000, 
    "franchise": 464, 
    "franchises": [
        464
    ], 
    "game_modes": [
        1
    ], 
    "games": [
        1070, 
        28029, 
        1073, 
        10039, 
        76229, 
        25311, 
        68287, 
        71455, 
        1188, 
        1715
    ], 
    "genres": [
        8
    ], 
    "id": 74422, 
    "keywords": [
        1286
    ], 
    "name": "Predator", 
    "platforms": [
        18, 
        27
    ], 
    "player_perspectives": [
        4
    ], 
    "popularity": 1.333333333333333, 
    "publishers": [
        1766
    ], 
    "release_dates": [
        {
            "category": 0, 
            "date": 573955200000, 
            "human": "1988-Mar-10", 
            "m": 3, 
            "platform": 18, 
            "region": 5, 
            "y": 1988
        }, 
        {
            "category": 2, 
            "date": 599529600000, 
            "human": "1988", 
            "m": 12, 
            "platform": 27, 
            "region": 5, 
            "y": 1988
        }
    ], 
    "slug": "predator--1", 
    "tags": [
        1, 
        18, 
        268435464, 
        536872198, 
        1073741828
    ], 
    "themes": [
        1, 
        18
    ], 
    "updated_at": 1517270782356, 
    "url": "https://www.igdb.com/games/predator--1"
}