{
    "category": 0, 
    "cover": {
        "cloudinary_id": "scoctemttvvuzmnrjwxb", 
        "height": 169, 
        "url": "//images.igdb.com/igdb/image/upload/t_thumb/scoctemttvvuzmnrjwxb.jpg", 
        "width": 300
    }, 
    "created_at": 1497969795807, 
    "developers": [
        12991
    ], 
    "esrb": {
        "rating": 3
    }, 
    "first_release_date": 1495584000000, 
    "game_engines": [
        206
    ], 
    "game_modes": [
        1
    ], 
    "games": [
        51485, 
        34919, 
        16468, 
        40524, 
        55289, 
        68324, 
        22690, 
        37022, 
        25646, 
        10039
    ], 
    "genres": [
        32, 
        33
    ], 
    "id": 38487, 
    "keywords": [
        101, 
        1411
    ], 
    "name": "SWIPE!", 
    "pegi": {
        "rating": 1
    }, 
    "platforms": [
        6, 
        37
    ], 
    "player_perspectives": [
        3
    ], 
    "popularity": 1.666666666666667, 
    "publishers": [
        12991
    ], 
    "release_dates": [
        {
            "category": 0, 
            "date": 1501113600000, 
            "human": "2017-Jul-27", 
            "m": 7, 
            "platform": 37, 
            "region": 2, 
            "y": 2017
        }, 
        {
            "category": 0, 
            "date": 1495584000000, 
            "human": "2017-May-24", 
            "m": 5, 
            "platform": 6, 
            "region": 8, 
            "y": 2017
        }
    ], 
    "screenshots": [
        {
            "cloudinary_id": "mu8swqd50sfypvwtai5w", 
            "height": 652, 
            "url": "//images.igdb.com/igdb/image/upload/t_thumb/mu8swqd50sfypvwtai5w.jpg", 
            "width": 869
        }, 
        {
            "cloudinary_id": "ogpii02rdpu2s5cfkrzu", 
            "height": 650, 
            "url": "//images.igdb.com/igdb/image/upload/t_thumb/ogpii02rdpu2s5cfkrzu.jpg", 
            "width": 869
        }, 
        {
            "cloudinary_id": "cahn8o4jzwatnxqgtqrg", 
            "height": 651, 
            "url": "//images.igdb.com/igdb/image/upload/t_thumb/cahn8o4jzwatnxqgtqrg.jpg", 
            "width": 865
        }
    ], 
    "slug": "swipe", 
    "status": 2, 
    "summary": "The best games are simple, challenging, and yet never frustrating. That's what makes SWIPE! so ridiculously fun!   \n   \n Make sure none of your sliders are ever caught touching the color red or each other. They can also never be left floating in midair. When a GREEN piece turns yellow, it's time for some fast action!   \n   \nSimple? Yes, but not boring!", 
    "tags": [
        1, 
        35, 
        268435488, 
        268435489, 
        536871013, 
        536872323, 
        1073741827
    ], 
    "themes": [
        1, 
        35
    ], 
    "updated_at": 1518013845198, 
    "url": "https://www.igdb.com/games/swipe", 
    "websites": [
        {
            "category": 5, 
            "url": "https://twitter.com/GabesGames1"
        }, 
        {
            "category": 1, 
            "url": "https://gabesgamesonline.yolasite.com/"
        }
    ]
}