{
    "category": 0, 
    "cover": {
        "cloudinary_id": "d3s4mkbksnxxhfs0nbb1", 
        "height": 700, 
        "url": "//images.igdb.com/igdb/image/upload/t_thumb/d3s4mkbksnxxhfs0nbb1.jpg", 
        "width": 498
    }, 
    "created_at": 1390768702539, 
    "first_release_date": 757296000000, 
    "games": [
        75962, 
        46815, 
        75964, 
        75858, 
        75857, 
        75853, 
        68609, 
        55058, 
        50726, 
        50704
    ], 
    "genres": [
        4
    ], 
    "id": 4367, 
    "name": "Street Fighter II: Special Champion Edition", 
    "platforms": [
        29, 
        5
    ], 
    "popularity": 1.333333333333333, 
    "publishers": [
        37
    ], 
    "pulse_count": 2, 
    "release_dates": [
        {
            "category": 0, 
            "date": 1217289600000, 
            "human": "2008-Jul-29", 
            "m": 7, 
            "platform": 5, 
            "region": 5, 
            "y": 2008
        }, 
        {
            "category": 0, 
            "date": 1224201600000, 
            "human": "2008-Oct-17", 
            "m": 10, 
            "platform": 5, 
            "region": 1, 
            "y": 2008
        }, 
        {
            "category": 0, 
            "date": 1223856000000, 
            "human": "2008-Oct-13", 
            "m": 10, 
            "platform": 5, 
            "region": 2, 
            "y": 2008
        }, 
        {
            "category": 2, 
            "date": 757296000000, 
            "human": "1993", 
            "m": 12, 
            "platform": 29, 
            "y": 1993
        }
    ], 
    "screenshots": [
        {
            "cloudinary_id": "iubma8gluhjcnereaeb8", 
            "height": 201, 
            "url": "//images.igdb.com/igdb/image/upload/t_thumb/iubma8gluhjcnereaeb8.jpg", 
            "width": 256
        }, 
        {
            "cloudinary_id": "cq9mlql6wb0irz2bq8zl", 
            "height": 201, 
            "url": "//images.igdb.com/igdb/image/upload/t_thumb/cq9mlql6wb0irz2bq8zl.jpg", 
            "width": 256
        }, 
        {
            "cloudinary_id": "imec8zs8cb4shbtqmezz", 
            "height": 201, 
            "url": "//images.igdb.com/igdb/image/upload/t_thumb/imec8zs8cb4shbtqmezz.jpg", 
            "width": 256
        }, 
        {
            "cloudinary_id": "tdfyxdjbogafs98htzpv", 
            "height": 201, 
            "url": "//images.igdb.com/igdb/image/upload/t_thumb/tdfyxdjbogafs98htzpv.jpg", 
            "width": 256
        }, 
        {
            "cloudinary_id": "iscbgqbldbrs8tnh3u7h", 
            "height": 201, 
            "url": "//images.igdb.com/igdb/image/upload/t_thumb/iscbgqbldbrs8tnh3u7h.jpg", 
            "width": 256
        }, 
        {
            "cloudinary_id": "syoaytwn4z91eltpbe1j", 
            "height": 201, 
            "url": "//images.igdb.com/igdb/image/upload/t_thumb/syoaytwn4z91eltpbe1j.jpg", 
            "width": 256
        }
    ], 
    "slug": "street-fighter-ii-special-champion-edition-c6119b36-b741-4f18-b839-ef685f020f7f", 
    "summary": "STREET FIGHTER II doesn't try to fool you with a fancy name that will entice you to try it no, the gameplay itself is enough to convince even the most discriminating gamer that this is a stellar game. There are eight fighters to choose from, each with a unique fighting style and special attacks. But your opponents also have special attacks Ken's Dragon Punch, Dhalsim's Yoga Flame, Zangief's pile driver, and Guile's Sonic Boom so a good defense is just as important as a potent offense. Through all kinds of diverse and awesome-looking environments, you'll go face-to-face against some of the meanest and nastiest street fighters this side of a honky tonk. Bring the arcade home and get ready to rumble with STREET FIGHTER II.", 
    "tags": [
        268435460
    ], 
    "updated_at": 1518012032323, 
    "url": "https://www.igdb.com/games/street-fighter-ii-special-champion-edition-c6119b36-b741-4f18-b839-ef685f020f7f"
}